MANIFEST.in
README.rst
setup.cfg
setup.py
bin/__init__.py
gitdata/__init__.py
gitdata/git.py
gitdata.egg-info/PKG-INFO
gitdata.egg-info/SOURCES.txt
gitdata.egg-info/dependency_links.txt
gitdata.egg-info/entry_points.txt
gitdata.egg-info/top_level.txt