Metadata-Version: 1.1
Name: gitdata
Version: 0.0.2
Summary: Storage the data files in ssh servers
Home-page: https://github.com/juanpabloaj/gitdata
Author: JuanPablo AJ
Author-email: jpabloaj@gmail.com
License: MIT
Platform: UNKNOWN
Classifier: Programming Language :: Python :: 2.7
